matomo_core/__init__.py
matomo_core/constants.py
matomo_core/core.py
matomo_core/py.typed
matomo_core/trackers.py
matomo_core-0.3.2.dist-info/METADATA
matomo_core-0.3.2.dist-info/WHEEL
matomo_core-0.3.2.dist-info/RECORD
